yvpn/__init__.py
yvpn/admin.py
yvpn/api_calls.py
yvpn/config.py
yvpn/endpoint.py
yvpn/main.py
yvpn/requirements.txt
yvpn/util.py
yvpn/wireguard.py
yvpn-0.2.0.dist-info/entry_points.txt
yvpn-0.2.0.dist-info/LICENSE
yvpn-0.2.0.dist-info/WHEEL
yvpn-0.2.0.dist-info/METADATA
yvpn-0.2.0.dist-info/RECORD
