Metadata-Version: 2.1
Name: yvpn
Version: 0.2.0
Summary: Command line tool to manage yvpn endpoints
License: GPL-3.0-or-later
Author: Ben Simcox
Author-email: ben@bnsmcx.com
Requires-Python: >=3.10,<4.0
Classifier: License :: OSI Approved :: GNU General Public License v3 or later (GPLv3+)
Classifier: Programming Language :: Python :: 3
Classifier: Programming Language :: Python :: 3.10
Requires-Dist: paramiko (>=2.11.0,<3.0.0)
Requires-Dist: requests (>=2.28.1,<3.0.0)
Requires-Dist: typer[all] (>=0.6.1,<0.7.0)
